separableconv/__init__.py
separableconv/version.py
separableconv/nn/__init__.py
separableconv/nn/base.py
separableconv/nn/conv.py
separableconv/nn/lazy.py
separableconv_torch-0.1.0.dist-info/LICENSE
separableconv_torch-0.1.0.dist-info/METADATA
separableconv_torch-0.1.0.dist-info/WHEEL
separableconv_torch-0.1.0.dist-info/top_level.txt
separableconv_torch-0.1.0.dist-info/RECORD
